pmoired/Model definitions and examples.ipynb
pmoired/Rosseland_SATLAS_dwarfs.dat
pmoired/Rosseland_SATLAS_giants.dat
pmoired/__init__.py
pmoired/chi2map.py
pmoired/dpfit.py
pmoired/dw.py
pmoired/microprogress.py
pmoired/newVltiHzn_obsDoors.txt
pmoired/noisemodel.py
pmoired/oicandid.py
pmoired/oicorr.py
pmoired/oifake.py
pmoired/oifast.py
pmoired/oifits.py
pmoired/oimodels.py
pmoired/oitest.py
pmoired/oitf.py
pmoired/satlas.py
pmoired/speedtest.py
pmoired/tellcorr.py
pmoired/test_Vmodels.py
pmoired/transir_gravity.pckl
pmoired/ulensBin.py
pmoired/ulensBin2.py
pmoired/wb.py
pmoired-1.3.10.dist-info/licenses/LICENCE.txt
pmoired-1.3.10.dist-info/METADATA
pmoired-1.3.10.dist-info/WHEEL
pmoired-1.3.10.dist-info/top_level.txt
pmoired-1.3.10.dist-info/RECORD
