Metadata-Version: 2.4
Name: pmoired
Version: 1.3.10
Summary: Display and fit Optical (spectro-)Interferometric OIFITS data
Author-email: Antoine Mérand <amerand@eso.org>
License: Copyright (c) 2020-2023, Antoine Méand
Project-URL: Repository, https://github.com/amerand/PMOIRED
Project-URL: Issues, https://github.com/amerand/PMOIRED/issues
Project-URL: Publications, https://ui.adsabs.harvard.edu/public-libraries/dz7RG915Swq5yAB1KwmgTA
Keywords: optical interferometry,visualization,display,OIFITS,data modelling,astrophysics
Classifier: Programming Language :: Python :: 3
Classifier: Operating System :: OS Independent
Classifier: Development Status :: 5 - Production/Stable
Classifier: Intended Audience :: Science/Research
Classifier: License :: OSI Approved :: BSD License
Classifier: Topic :: Scientific/Engineering :: Astronomy
Classifier: Topic :: Scientific/Engineering :: Visualization
Requires-Python: >=3.8
License-File: LICENCE.txt
Requires-Dist: scipy>=1.10.0
Requires-Dist: numpy>=2.0.0
Requires-Dist: matplotlib>=3.8.0
Requires-Dist: astropy>=6.0.0
Requires-Dist: astroquery>=0.4.4
Requires-Dist: importlib_resources; python_version < "3.9"
Requires-Dist: pyserial>=3.5
Dynamic: license-file
